xarray_healpy/__init__.py
xarray_healpy/_healpy.py
xarray_healpy/conversions.py
xarray_healpy/grid.py
xarray_healpy/operations.py
xarray_healpy/regridder.py
xarray_healpy/utils.py
xarray_healpy/interpolation/bilinear.py
xarray_healpy/interpolation/mask.py
xarray_healpy-2025.3.2.dist-info/LICENSE
xarray_healpy-2025.3.2.dist-info/METADATA
xarray_healpy-2025.3.2.dist-info/WHEEL
xarray_healpy-2025.3.2.dist-info/top_level.txt
xarray_healpy-2025.3.2.dist-info/RECORD
