Metadata-Version: 2.2
Name: xarray-healpy
Version: 2025.3.2
License: MIT
Requires-Python: >=3.10
License-File: LICENSE
Requires-Dist: xarray>=2023.11.0
Requires-Dist: healpy
Requires-Dist: sparse
Requires-Dist: opt_einsum
Requires-Dist: numba
Requires-Dist: numpy
Requires-Dist: sparse
Requires-Dist: scikit-learn
Requires-Dist: opt_einsum
Requires-Dist: cdshealpix
Requires-Dist: astropy
